asynciolimiter/__init__.py
asynciolimiter/py.typed
asynciolimiter-1.2.0.dist-info/METADATA
asynciolimiter-1.2.0.dist-info/WHEEL
asynciolimiter-1.2.0.dist-info/licenses/LICENSE
asynciolimiter-1.2.0.dist-info/RECORD
