Metadata-Version: 2.4
Name: asynciolimiter
Version: 1.2.0
Summary: Rate limiter for Async IO
Project-URL: Homepage, https://github.com/bharel/asynciolimiter
Project-URL: Documentation, https://asynciolimiter.readthedocs.io/en/latest/
Project-URL: Source, https://github.com/bharel/asynciolimiter
Project-URL: Changelog, https://github.com/bharel/asynciolimiter/blob/master/changelog.md
Author-email: Bar Harel <bzvi7919@gmail.com>
License-File: LICENSE
Keywords: asyncio,rate limiter,throttling
Classifier: Development Status :: 5 - Production/Stable
Classifier: Framework :: AsyncIO
Classifier: Intended Audience :: Developers
Classifier: License :: OSI Approved :: MIT License
Classifier: Operating System :: OS Independent
Classifier: Programming Language :: Python :: 3
Classifier: Programming Language :: Python :: 3.9
Classifier: Programming Language :: Python :: 3.10
Classifier: Programming Language :: Python :: 3.11
Classifier: Programming Language :: Python :: 3.12
Classifier: Programming Language :: Python :: 3.13
Classifier: Programming Language :: Python :: 3.14
Classifier: Topic :: Internet
Classifier: Topic :: Software Development :: Libraries
Classifier: Topic :: Utilities
Classifier: Typing :: Typed
Requires-Python: >=3.9
Provides-Extra: dev
Requires-Dist: flake8; extra == 'dev'
Requires-Dist: git-cliff; extra == 'dev'
Requires-Dist: isort; extra == 'dev'
Requires-Dist: mypy; extra == 'dev'
Requires-Dist: sphinx; extra == 'dev'
Requires-Dist: sphinx-rtd-theme; extra == 'dev'
